seekcamera/__init__.py
seekcamera/_clib.py
seekcamera/camera.py
seekcamera/error.py
seekcamera/version.py
seekcamera_python-1.1.1.data/data/examples/seekcamera-opencv.py
seekcamera_python-1.1.1.data/data/examples/seekcamera-simple.py
seekcamera_python-1.1.1.dist-info/LICENSE
seekcamera_python-1.1.1.dist-info/METADATA
seekcamera_python-1.1.1.dist-info/WHEEL
seekcamera_python-1.1.1.dist-info/top_level.txt
seekcamera_python-1.1.1.dist-info/RECORD
