Metadata-Version: 2.1
Name: seekcamera-python
Version: 1.1.1
Summary: Seek Thermal SDK Python Language Bindings
Home-page: https://github.com/seekthermal/seekcamera-python
Author: Seek Thermal Incorporated
Author-email: open-source@thermal.com
License: Apache License 2.0
Platform: UNKNOWN
Classifier: Programming Language :: Python :: 3
Classifier: Operating System :: OS Independent
Classifier: Intended Audience :: Developers
Requires-Python: >=3.0
License-File: LICENSE
Requires-Dist: numpy (>=1)
